dewan_manual_curation/__init__.py
dewan_manual_curation/__main__.py
dewan_manual_curation/gui.py
dewan_manual_curation/manual_curation.py
dewan_manual_curation/_components/__init__.py
dewan_manual_curation/_components/analog_trace.py
dewan_manual_curation/_components/callbacks.py
dewan_manual_curation/_components/funcs.py
dewan_manual_curation/_components/maxprojection.py
dewan_manual_curation-2.4.dist-info/METADATA
dewan_manual_curation-2.4.dist-info/WHEEL
dewan_manual_curation-2.4.dist-info/top_level.txt
dewan_manual_curation-2.4.dist-info/RECORD
