Metadata-Version: 2.4
Name: dewan_manual_curation
Version: 2.4
Summary: Interface for manually curating various analog traces
Author-email: Austin Pauley <austin2118ace@gmail.com>
Requires-Python: <3.12,>=3.10
Requires-Dist: PySide6==6.7.2
Requires-Dist: pyqtdarktheme==2.1.0
Requires-Dist: shapely
Requires-Dist: matplotlib>=3.9.2
Requires-Dist: pandas>2.0.0
Requires-Dist: scikit-learn>=1.5.1
Requires-Dist: numpy>2.0
